excel_util/__init__.py
excel_util-0.0.4.dist-info/METADATA
excel_util-0.0.4.dist-info/WHEEL
excel_util-0.0.4.dist-info/top_level.txt
excel_util-0.0.4.dist-info/RECORD
